README.rst
requirements.txt
setup.cfg
setup.py
tox.ini
contrib/irc-config.py
contrib/slack-config.py
docs/source/_static/team_chat.png
teamchat/__init__.py
teamchat/cli.py
teamchat.egg-info/PKG-INFO
teamchat.egg-info/SOURCES.txt
teamchat.egg-info/dependency_links.txt
teamchat.egg-info/entry_points.txt
teamchat.egg-info/not-zip-safe
teamchat.egg-info/pbr.json
teamchat.egg-info/requires.txt
teamchat.egg-info/top_level.txt
teamchat/ansible/enable-bot.yml
teamchat/ansible/templates/service.conf.j2
teamchat/errbot/plugins/teamchat.plug
teamchat/errbot/plugins/teamchat.py