Metadata-Version: 1.2
Name: teamchat
Version: 0.1.0
Summary: teamchat breaks the barriers between communities and instant messaging platforms
Home-page: https://github.com/dmsimard/teamchat
Author: David Moreau-Simard
Author-email: me@dmsimard.com
License: UNKNOWN
Platform: UNKNOWN
Classifier: Intended Audience :: Information Technology
Classifier: Intended Audience :: System Administrators
Classifier: Intended Audience :: Developers
Classifier: Topic :: Utilities
Classifier: License :: OSI Approved :: Apache Software License
Classifier: Programming Language :: Python :: 3
Classifier: Development Status :: 4 - Beta
Requires-Python: >=3.6
